CHANGES.rst
CONTRIBUTORS.rst
MANIFEST.in
README.rst
setup.cfg
setup.py
docs/LICENSE.GPL
docs/LICENSE.rst
docs/index.rst
docs/screenshot.png
src/collective/__init__.py
src/collective.geo.faceted.egg-info/PKG-INFO
src/collective.geo.faceted.egg-info/SOURCES.txt
src/collective.geo.faceted.egg-info/dependency_links.txt
src/collective.geo.faceted.egg-info/entry_points.txt
src/collective.geo.faceted.egg-info/namespace_packages.txt
src/collective.geo.faceted.egg-info/not-zip-safe
src/collective.geo.faceted.egg-info/requires.txt
src/collective.geo.faceted.egg-info/top_level.txt
src/collective/geo/__init__.py
src/collective/geo/faceted/__init__.py
src/collective/geo/faceted/configure.zcml
src/collective/geo/faceted/interfaces.py
src/collective/geo/faceted/setuphandlers.py
src/collective/geo/faceted/testing.py
src/collective/geo/faceted/testing.zcml
src/collective/geo/faceted/browser/__init__.py
src/collective/geo/faceted/browser/configure.zcml
src/collective/geo/faceted/browser/faceted-map-view.pt
src/collective/geo/faceted/browser/mapviewlet.pt
src/collective/geo/faceted/browser/mapviewlet.py
src/collective/geo/faceted/browser/view.py
src/collective/geo/faceted/browser/overrides/.gitkeep
src/collective/geo/faceted/browser/static/update_map.js
src/collective/geo/faceted/locales/collective.geo.faceted.pot
src/collective/geo/faceted/locales/update.sh
src/collective/geo/faceted/locales/en/LC_MESSAGES/collective.geo.faceted.po
src/collective/geo/faceted/locales/fr/LC_MESSAGES/collective.geo.faceted.po
src/collective/geo/faceted/profiles/default/browserlayer.xml
src/collective/geo/faceted/profiles/default/metadata.xml
src/collective/geo/faceted/profiles/default/registry.xml
src/collective/geo/faceted/profiles/default/types/Collection.xml
src/collective/geo/faceted/profiles/default/types/Document.xml
src/collective/geo/faceted/profiles/default/types/Event.xml
src/collective/geo/faceted/profiles/testing/metadata.xml
src/collective/geo/faceted/profiles/uninstall/browserlayer.xml
src/collective/geo/faceted/tests/__init__.py
src/collective/geo/faceted/tests/test_robot.py
src/collective/geo/faceted/tests/test_setup.py
src/collective/geo/faceted/tests/test_view.py
src/collective/geo/faceted/tests/test_viewlet.py
src/collective/geo/faceted/tests/test_widget.py
src/collective/geo/faceted/tests/robot/test_example.robot
src/collective/geo/faceted/widget/__init__.py
