Metadata-Version: 1.1
Name: collective.geo.faceted
Version: 1.0.1
Summary: A map view for a facetednav
Home-page: https://pypi.python.org/pypi/collective.geo.faceted
Author: Benoit Suttor
Author-email: bsuttor@imio.be
License: GPL version 2
Keywords: Python Plone
Platform: UNKNOWN
Classifier: Environment :: Web Environment
Classifier: Framework :: Plone
Classifier: Framework :: Plone :: 4.0
Classifier: Framework :: Plone :: 5.0
Classifier: Programming Language :: Python
Classifier: Programming Language :: Python :: 2.7
Classifier: Operating System :: OS Independent
Classifier: License :: OSI Approved :: GNU General Public License v2 (GPLv2)
